src/main/verilog/empty/CodeReceiver.v
module CodeReceiver
(
  input        clock,
  input        reset,
  input        io_input,
  output reg [7:0] io_output
);
  reg [2:0] countReg;
  reg [7:0] dataReg;
  reg [7:0] dataRegBuffer; // to store the value when in the process of receiving
  reg dataFull;

  // initialize
  initial begin
    countReg <= 3'h0;
    dataReg <= 8'h00;
    dataRegBuffer <= 8'h00;
    dataFull <= 1'b1;
  end

  always @(posedge clock) begin
    if (reset) begin
      countReg <= 3'h0;
      dataReg <= 8'h00;
      dataRegBuffer <= 8'h00;
      dataFull <= 1'b1;
    end
    else begin
      if (dataFull) begin 
        io_output <= dataRegBuffer; // maintain the current state
        if (io_input) begin // detect the start bit, jump directly to the receiving state
		  dataFull <= 0;
          dataReg <= 8'h00;
        end
      end
      else begin
      countReg <= countReg + 1;
      if (countReg < 3'h7) begin
        dataReg <= (dataReg << 1);
        dataReg[0] <= io_input;
        dataFull <= 0;
        io_output <= dataRegBuffer;
      end
      else begin
        countReg <= 3'h0; // the data is full
        io_output <= dataReg;
        dataRegBuffer <= dataReg;
        if (io_input) begin // detect the start bit, jump directly to the receiving state
		      dataFull <= 0;
          dataReg <= 8'h00;
        end
        else begin // maintain the current state
          dataFull <= 1;
        end
      end
      end
    end
  end
endmodule

src/test/verilog/empty/CodeReceiverTester.v
`timescale 1ns/1ns

`include "../../../main/verilog/empty/CodeReceiver.v"

module CodeReceiver_tb;

  // Inputs
  reg clock;
  reg reset;
  reg io_input;

  // Outputs
  wire [7:0] io_output;

  // Instantiate the CodeReceiver module
  CodeReceiver uut (
    .clock(clock),
    .reset(reset),
    .io_input(io_input),
    .io_output(io_output)
  );

  // Clock generation
  always begin
    #5 clock = ~clock;
  end

  // Initial values
  initial begin
    clock = 1;
    reset = 0;
    io_input = 0;

    // Reset the CodeReceiver module
    reset = 1;
    #10 reset = 0;

    // Stimulus generation
    // 1,0,0,1,0,1,0,1
    // 1,0,1,0,0,1,1,1
    // 1,0,0,1,0,1,0,1
    io_input = 1;
    #10 io_input = 0;
    #10 io_input = 0;
    #10 io_input = 1;
    #10 io_input = 0;
    #10 io_input = 1;
    #10 io_input = 0;
    #10 io_input = 1;
    #10 io_input = 0;
    #10 io_input = 0;
    #10 io_input = 0;

    #10 io_input = 1;
    #10 io_input = 0;
    #10 io_input = 1;
    #10 io_input = 0;
    #10 io_input = 0;
    #10 io_input = 1;
    #10 io_input = 1;
    #10 io_input = 1;
    #10 io_input = 0;
    #10 io_input = 0;
    #10 io_input = 0;

    #10 io_input = 1;
    #10 io_input = 0;
    #10 io_input = 0;
    #10 io_input = 1;
    #10 io_input = 0;
    #10 io_input = 1;
    #10 io_input = 0;
    #10 io_input = 1;

    // Finish the simulation
    #50 $finish;
  end

  // Simulate the testbench
  initial begin
    $dumpfile("CodeReceiver_tb.vcd");
    $dumpvars(0, CodeReceiver_tb);
    $display("Starting simulation...");
    $monitor("clock = %b, reset = %b, io_input = %b", clock, reset, io_input);
    $monitor("io_output = %b", io_output);
    $display("");
    $display("Simulation results:");
    $display("-------------------");
    $display("");

    // Run the simulation for some time
    #3000;

    $display("");
    $display("Simulation finished.");
    $display("Exiting simulation...");
    $finish;
  end

endmodule

src/test/verilog/empty/CodeReceiver_tb.vcd
$date
	Fri Oct 27 13:01:40 2023
$end
$version
	Icarus Verilog
$end
$timescale
	1ns
$end
$scope module CodeReceiver_tb $end
$var wire 8 ! io_output [7:0] $end
$var reg 1 " clock $end
$var reg 1 # io_input $end
$var reg 1 $ reset $end
$scope module uut $end
$var wire 1 " clock $end
$var wire 1 # io_input $end
$var wire 1 $ reset $end
$var reg 3 % countReg [2:0] $end
$var reg 1 & dataFull $end
$var reg 8 ' dataReg [7:0] $end
$var reg 8 ( dataRegBuffer [7:0] $end
$var reg 8 ) io_output [7:0] $end
$upscope $end
$upscope $end
$enddefinitions $end
#0
$dumpvars
bx )
b0 (
b0 '
1&
b0 %
1$
0#
1"
bx !
$end
#5
0"
#10
0&
b0 !
b0 )
1"
1#
0$
#15
0"
#20
b1 %
1"
0#
#25
0"
#30
b10 %
1"
#35
0"
#40
b1 '
b11 %
1"
1#
#45
0"
#50
b10 '
b100 %
1"
0#
#55
0"
#60
b101 '
b101 %
1"
1#
#65
0"
#70
b1010 '
b110 %
1"
0#
#75
0"
#80
b10101 '
b111 %
1"
1#
#85
0"
#90
1&
b10101 (
b10101 !
b10101 )
b0 %
1"
0#
#95
0"
#100
1"
#105
0"
#110
1"
#115
0"
#120
b0 '
0&
1"
1#
#125
0"
#130
b1 %
1"
0#
#135
0"
#140
b1 '
b10 %
1"
1#
#145
0"
#150
b10 '
b11 %
1"
0#
#155
0"
#160
b100 '
b100 %
1"
#165
0"
#170
b1001 '
b101 %
1"
1#
#175
0"
#180
b10011 '
b110 %
1"
#185
0"
#190
b100111 '
b111 %
1"
#195
0"
#200
1&
b100111 (
b100111 !
b100111 )
b0 %
1"
0#
#205
0"
#210
1"
#215
0"
#220
1"
#225
0"
#230
b0 '
0&
1"
1#
#235
0"
#240
b1 %
1"
0#
#245
0"
#250
b10 %
1"
#255
0"
#260
b1 '
b11 %
1"
1#
#265
0"
#270
b10 '
b100 %
1"
0#
#275
0"
#280
b101 '
b101 %
1"
1#
#285
0"
#290
b1010 '
b110 %
1"
0#
#295
0"
#300
b10101 '
b111 %
1"
1#
#305
0"
#310
b0 '
b10101 (
b10101 !
b10101 )
b0 %
1"
#315
0"
#320
b1 '
b1 %
1"
#325
0"
#330
b11 '
b10 %
1"
#335
0"
#340
b111 '
b11 %
1"
#345
0"
#350
b1111 '
b100 %
1"
